{
  "sponsors": {
    "full": [
      {
        "url": "https://developers.google.com/live/chrome/",
        "img": "chrome.png",
        "blurb": "Google’s mission is to organise the world’s information and make it universally accessible and useful."
      }
    ],
    "half": [
      {
        "url": "http://google.com",
        "img": "sponsor.png"
      }
    ],
    "small": [
      {
        "url": "http://google.com",
        "img": "sponsor.png"
      },
      {
        "url": "http://google.com",
        "img": "sponsor.png"
      },
      {
        "url": "http://google.com",
        "img": "sponsor.png"
      },
      {
        "url": "http://google.com",
        "img": "sponsor.png"
      },
      {
        "url": "http://google.com",
        "img": "sponsor.png"
      },
      {
        "url": "http://google.com",
        "img": "sponsor.png"
      },
      {
        "url": "http://google.com",
        "img": "sponsor.png"
      },
      {
        "url": "http://google.com",
        "img": "sponsor.png"
      }
    ]
  }
}
